github_star_import/__init__.py
github_star_import/__main__.py
github_star_import/_github_star_import.c
github_star_import/_github_star_import.cpython-35m-darwin.so
github_star_import/_github_star_import.pyx
github_star_import/cli.py
github_star_import-0.2.0.dist-info/AUTHORS.rst
github_star_import-0.2.0.dist-info/LICENSE
github_star_import-0.2.0.dist-info/METADATA
github_star_import-0.2.0.dist-info/WHEEL
github_star_import-0.2.0.dist-info/entry_points.txt
github_star_import-0.2.0.dist-info/top_level.txt
github_star_import-0.2.0.dist-info/RECORD
